SURPY/soap.py
SURPY-2.1.0.dist-info/METADATA
SURPY-2.1.0.dist-info/WHEEL
SURPY-2.1.0.dist-info/top_level.txt
SURPY-2.1.0.dist-info/RECORD
