Metadata-Version: 2.1
Name: SURPY
Version: 2.1.0
Summary: SURPY python for surgical data analysis
Home-page: https://github.com/sasurasa/
Author: Surasak Sangkhathat
Author-email: s.sangkhathat@gmail.com
License: Prince of Songkla University
